erddaplogs/_version.py
erddaplogs/logparse.py
erddaplogs/plot_functions.py
erddaplogs-0.1.4.dist-info/LICENSE
erddaplogs-0.1.4.dist-info/METADATA
erddaplogs-0.1.4.dist-info/WHEEL
erddaplogs-0.1.4.dist-info/top_level.txt
erddaplogs-0.1.4.dist-info/RECORD
