Metadata-Version: 2.1
Name: erddaplogs
Version: 0.1.4
Summary: Parse log files from an ERDDAP server
Maintainer-email: Callum Rollo <c.rollo@outlook.com>
License: MIT License
Project-URL: documentation, https://github.com/callumrollo/erddaplogs
Project-URL: homepage, https://github.com/callumrollo/erddaplogs
Project-URL: repository, https://github.com/callumrollo/erddaplogs
Classifier: Programming Language :: Python :: 3 :: Only
Classifier: Programming Language :: Python :: 3.8
Classifier: Programming Language :: Python :: 3.9
Classifier: Programming Language :: Python :: 3.10
Classifier: Programming Language :: Python :: 3.11
Classifier: Programming Language :: Python :: 3.12
Requires-Python: >=3.8
License-File: LICENSE
Requires-Dist: numpy
Requires-Dist: polars >=1.1.0
Requires-Dist: requests
Requires-Dist: pyarrow
Requires-Dist: user-agents
Provides-Extra: plotting
Requires-Dist: iso3166 ; extra == 'plotting'
Requires-Dist: cartopy ; extra == 'plotting'
Requires-Dist: matplotlib ; extra == 'plotting'
Provides-Extra: test
Requires-Dist: iso3166 ; extra == 'test'
Requires-Dist: cartopy ; extra == 'test'
Requires-Dist: matplotlib ; extra == 'test'
Requires-Dist: pytest ; extra == 'test'
